{"cameraMode":{"drawMode":0,"name":"Shaded","section":"Shading Mode"},"sceneLighting":true,"audioPlay":false,"sceneViewState":{"showFog":true,"showMaterialUpdate":false,"showSkybox":true,"showFlares":true,"showImageEffects":true,"showParticleSystems":true},"in2DMode":false,"pivot":{"x":15.600000381469727,"y":74.749755859375,"z":-0.7100000381469727},"rotation":{"x":-0.15418657660484315,"y":-0.008302135393023491,"z":0.0012956069549545646,"w":-0.988006591796875},"size":94.9356689453125,"orthographic":false}